funniest/__init__.py
filbuktools-0.1.dist-info/METADATA
filbuktools-0.1.dist-info/WHEEL
filbuktools-0.1.dist-info/top_level.txt
filbuktools-0.1.dist-info/RECORD
