Metadata-Version: 2.1
Name: filbuktools
Version: 0.1
Summary: filbuktools
Home-page: http://github.com/filbuk/filbuktools
Author: filbuk
Author-email: filbuk.wen@gmail.com
License: MIT
Platform: UNKNOWN
